invenio_oauthclient/__init__.py
invenio_oauthclient/_compat.py
invenio_oauthclient/admin.py
invenio_oauthclient/config.py
invenio_oauthclient/errors.py
invenio_oauthclient/ext.py
invenio_oauthclient/models.py
invenio_oauthclient/oauth.py
invenio_oauthclient/proxies.py
invenio_oauthclient/signals.py
invenio_oauthclient/tasks.py
invenio_oauthclient/utils.py
invenio_oauthclient/alembic/1758275763_extra_data_jsonb.py
invenio_oauthclient/alembic/44ab9963e8cf_create_oauthclient_branch.py
invenio_oauthclient/alembic/7def990b852e_add_expires_at_and_refresh_token_to_.py
invenio_oauthclient/alembic/97bbc733896c_create_oauthclient_tables.py
invenio_oauthclient/alembic/__init__.py
invenio_oauthclient/alembic/aaa265b0afa6_move_useridentity_to_acconuts.py
invenio_oauthclient/alembic/bff1f190b9bd_add_timestamp_oauthclient.py
invenio_oauthclient/contrib/__init__.py
invenio_oauthclient/contrib/cern.py
invenio_oauthclient/contrib/cern_openid.py
invenio_oauthclient/contrib/eosc_aai.py
invenio_oauthclient/contrib/github.py
invenio_oauthclient/contrib/globus.py
invenio_oauthclient/contrib/openaire_aai.py
invenio_oauthclient/contrib/orcid.py
invenio_oauthclient/contrib/settings.py
invenio_oauthclient/contrib/keycloak/__init__.py
invenio_oauthclient/contrib/keycloak/handlers.py
invenio_oauthclient/contrib/keycloak/helpers.py
invenio_oauthclient/contrib/keycloak/settings.py
invenio_oauthclient/handlers/__init__.py
invenio_oauthclient/handlers/authorized.py
invenio_oauthclient/handlers/base.py
invenio_oauthclient/handlers/decorators.py
invenio_oauthclient/handlers/refresh.py
invenio_oauthclient/handlers/rest.py
invenio_oauthclient/handlers/token.py
invenio_oauthclient/handlers/ui.py
invenio_oauthclient/handlers/utils.py
invenio_oauthclient/templates/invenio_oauthclient/_macros.html
invenio_oauthclient/templates/invenio_oauthclient/base.html
invenio_oauthclient/templates/invenio_oauthclient/base_cover.html
invenio_oauthclient/templates/invenio_oauthclient/login_user.html
invenio_oauthclient-6.1.3.dist-info/licenses/AUTHORS.rst
invenio_oauthclient-6.1.3.dist-info/licenses/LICENSE
invenio_oauthclient-6.1.3.dist-info/METADATA
invenio_oauthclient-6.1.3.dist-info/WHEEL
invenio_oauthclient-6.1.3.dist-info/entry_points.txt
invenio_oauthclient-6.1.3.dist-info/top_level.txt
invenio_oauthclient-6.1.3.dist-info/RECORD
