Metadata-Version: 2.4
Name: invenio-oauthclient
Version: 6.1.3
Summary: "Invenio module that provides OAuth web authorization support."
Home-page: https://github.com/inveniosoftware/invenio-oauthclient
Author: CERN
Author-email: info@inveniosoftware.org
License: MIT
Keywords: invenio oauth authentication
Platform: any
Classifier: Development Status :: 5 - Production/Stable
Requires-Python: >=3.7
License-File: LICENSE
License-File: AUTHORS.rst
Requires-Dist: blinker>=1.4
Requires-Dist: Flask-OAuthlib-Invenio<2.0.0,>=1.0.0
Requires-Dist: invenio-accounts<7.0.0,>=6.0.0
Requires-Dist: invenio-base<3.0.0,>=2.0.0
Requires-Dist: invenio-i18n<4.0.0,>=3.0.0
Requires-Dist: invenio-mail<3.0.0,>=1.0.2
Requires-Dist: invenio-theme<5.0.0,>=4.0.0
Requires-Dist: oauthlib>=1.1.2
Requires-Dist: markupsafe>=2.1.5
Requires-Dist: requests-oauthlib>=0.6.2
Requires-Dist: uritools>=1.0.1
Requires-Dist: github3.py>=1.0.0a4
Requires-Dist: uritemplate>=3.0.1
Provides-Extra: tests
Requires-Dist: flask_admin>=1.6.0; extra == "tests"
Requires-Dist: pytest-black-ng>=0.4.0; extra == "tests"
Requires-Dist: httpretty>=0.8.14; extra == "tests"
Requires-Dist: invenio-userprofiles<5.0.0,>=4.0.0; extra == "tests"
Requires-Dist: mock>=1.3.0; extra == "tests"
Requires-Dist: oauthlib>=1.1.2; extra == "tests"
Requires-Dist: pytest-invenio<4.0.0,>=3.0.0; extra == "tests"
Requires-Dist: requests-oauthlib>=0.6.2; extra == "tests"
Requires-Dist: simplejson>=3.8; extra == "tests"
Requires-Dist: sphinx>=4.5; extra == "tests"
Requires-Dist: invenio-db[mysql,postgresql,versioning]<3.0.0,>=2.0.0; extra == "tests"
Provides-Extra: admin
Provides-Extra: docs
Provides-Extra: github
Provides-Extra: mysql
Provides-Extra: orcid
Provides-Extra: postgresql
Provides-Extra: sqlite
Dynamic: license-file
